steer_opencell_data/DataManager.py
steer_opencell_data/__init__.py
steer_opencell_data/database.db
steer_opencell_data-0.0.14.dist-info/licenses/LICENCE.txt
steer_opencell_data-0.0.14.dist-info/METADATA
steer_opencell_data-0.0.14.dist-info/WHEEL
steer_opencell_data-0.0.14.dist-info/top_level.txt
steer_opencell_data-0.0.14.dist-info/RECORD
