Metadata-Version: 2.4
Name: steer-opencell-data
Version: 0.0.14
Summary: STEER OpenCell Data - Data feed for STEER OpenCell
Author-email: Nicholas Siemons <nsiemons@stanford.edu>
License: MIT
Project-URL: Homepage, https://github.com/stanford-developers/steer-opencell-data/
Project-URL: Repository, https://github.com/stanford-developers/steer-opencell-data/
Classifier: Programming Language :: Python :: 3
Classifier: Operating System :: OS Independent
Requires-Python: >=3.10
License-File: LICENCE.txt
Requires-Dist: steer-core==0.1.39
Dynamic: license-file
